README.md
setup.py
tap_selligent/__init__.py
tap_selligent/schemas.py
tap_selligent.egg-info/PKG-INFO
tap_selligent.egg-info/SOURCES.txt
tap_selligent.egg-info/dependency_links.txt
tap_selligent.egg-info/entry_points.txt
tap_selligent.egg-info/requires.txt
tap_selligent.egg-info/top_level.txt