Metadata-Version: 1.1
Name: tap-selligent
Version: 0.0.2
Summary: Singer.io tap for extracting data from the Selligent API
Home-page: http://singer.io
Author: Stitch
Author-email: UNKNOWN
License: UNKNOWN
Platform: UNKNOWN
Classifier: Programming Language :: Python :: 3 :: Only
